openmtpk-0.9.7.dist-info/RECORD
openmtpk-0.9.7.dist-info/LICENSE
openmtpk-0.9.7.dist-info/WHEEL
openmtpk-0.9.7.dist-info/METADATA
openmtpk-0.9.7.dist-info/top_level.txt
openmtpk/_version.py
openmtpk/__init__.py
openmtpk/nt/nt.py
openmtpk/nt/_nt.cpython-38-x86_64-linux-gnu.so
openmtpk/nt/__init__.py
openmtpk/ml/ml.py
openmtpk/ml/__init__.py
openmtpk/ml/_ml.cpython-38-x86_64-linux-gnu.so
openmtpk/linalg/_linalg.cpython-38-x86_64-linux-gnu.so
openmtpk/linalg/linalg.py
openmtpk/linalg/__init__.py
openmtpk/calculus/calculus.py
openmtpk/calculus/_calculus.cpython-38-x86_64-linux-gnu.so
openmtpk/calculus/__init__.py
openmtpk/arithmetic/_arithmetic.cpython-38-x86_64-linux-gnu.so
openmtpk/arithmetic/arithmetic.py
openmtpk/arithmetic/__init__.py
