Metadata-Version: 2.1
Name: openmtpk
Version: 0.9.7
Summary: openMTPK Python API
Home-page: https://github.com/akielaries/openMTPK
Author: Akiel Aries
Author-email: akiel@akiel.org
Project-URL: Documentation, https://akielaries.github.io/openMTPK/
Project-URL: Bug Reports, https://github.com/akielaries/openMTPK/issues
Project-URL: Source Code, https://github.com/akielaries/openMTPK/
Keywords: openmtpk,example,pypi,package
Classifier: Development Status :: 4 - Beta
Classifier: Intended Audience :: Science/Research
Classifier: Intended Audience :: Developers
Classifier: Intended Audience :: Education
Classifier: Intended Audience :: Information Technology
Classifier: Topic :: Scientific/Engineering
Classifier: Topic :: Scientific/Engineering :: Mathematics
Classifier: Topic :: Scientific/Engineering :: Artificial Intelligence
Classifier: Topic :: Software Development
Classifier: Topic :: Software Development :: Build Tools
Classifier: Topic :: Software Development :: Libraries
Classifier: Topic :: Software Development :: Libraries :: Python Modules
Classifier: Topic :: Utilities
Classifier: Topic :: Education
Classifier: Topic :: Education :: Testing
Classifier: Topic :: Documentation
Classifier: Programming Language :: C++
Classifier: Programming Language :: C
Classifier: Programming Language :: Python :: 3
Classifier: Programming Language :: Python :: 3.6
Classifier: Programming Language :: Python :: 3.7
Classifier: Programming Language :: Python :: 3.8
Classifier: Programming Language :: Python :: 3.9
Classifier: Programming Language :: Python :: 3.10
Classifier: Programming Language :: Python :: 3 :: Only
Classifier: Programming Language :: Fortran
Classifier: Programming Language :: R
Classifier: Programming Language :: OCaml
Classifier: Operating System :: POSIX
Classifier: Operating System :: Unix
Classifier: Operating System :: MacOS
Requires-Python: >=3.6
Provides-Extra: dev
License-File: LICENSE
